gym_derk/__init__.py
gym_derk/action_keys.py
gym_derk/derk_app_instance.py
gym_derk/derk_server.py
gym_derk/enums.py
gym_derk/utils.py
gym_derk/app_build/asset-manifest.json
gym_derk/app_build/favicon.ico
gym_derk/app_build/index.html
gym_derk/app_build/manifest.json
gym_derk/app_build/static/css/2.fd0d5f55.chunk.css
gym_derk/app_build/static/css/2.fd0d5f55.chunk.css.map
gym_derk/app_build/static/css/3.795d0318.chunk.css
gym_derk/app_build/static/css/3.795d0318.chunk.css.map
gym_derk/app_build/static/css/4.588081fe.chunk.css
gym_derk/app_build/static/css/4.588081fe.chunk.css.map
gym_derk/app_build/static/css/main.2544af6f.chunk.css
gym_derk/app_build/static/css/main.2544af6f.chunk.css.map
gym_derk/app_build/static/js/2.60352daa.chunk.js
gym_derk/app_build/static/js/2.60352daa.chunk.js.LICENSE.txt
gym_derk/app_build/static/js/2.60352daa.chunk.js.map
gym_derk/app_build/static/js/3.f86b0217.chunk.js
gym_derk/app_build/static/js/3.f86b0217.chunk.js.map
gym_derk/app_build/static/js/4.05c378fe.chunk.js
gym_derk/app_build/static/js/4.05c378fe.chunk.js.LICENSE.txt
gym_derk/app_build/static/js/4.05c378fe.chunk.js.map
gym_derk/app_build/static/js/main.13a4303b.chunk.js
gym_derk/app_build/static/js/main.13a4303b.chunk.js.map
gym_derk/app_build/static/js/runtime-main.7dc5a749.js
gym_derk/app_build/static/js/runtime-main.7dc5a749.js.map
gym_derk/app_build/static/media/ArenaMap.67ee37db.glb
gym_derk/app_build/static/media/BountyPoster.7a4a3d6a.svg
gym_derk/app_build/static/media/Bullet.35b36172.glb
gym_derk/app_build/static/media/Changelog.1c364693.md
gym_derk/app_build/static/media/Crab.5939a931.glb
gym_derk/app_build/static/media/Dart.27a3a7be.glb
gym_derk/app_build/static/media/Duck.1df0709b.glb
gym_derk/app_build/static/media/EnergyModel05.c24d9b5b.png
gym_derk/app_build/static/media/EnergyModel052.dcd0ffd0.png
gym_derk/app_build/static/media/Gold.fd9993fb.png
gym_derk/app_build/static/media/Image0000.a88ec4c0.exr
gym_derk/app_build/static/media/Image0000.e25d7315.exr
gym_derk-1.1.1.dist-info/LICENSE
gym_derk-1.1.1.dist-info/METADATA
gym_derk-1.1.1.dist-info/WHEEL
gym_derk-1.1.1.dist-info/top_level.txt
gym_derk-1.1.1.dist-info/RECORD
