Metadata-Version: 2.1
Name: gym-derk
Version: 1.1.1
Summary: Derk OpenAI Gym Environment
Home-page: https://gym.derkgame.com
Author: Mount Rouke
Author-email: contact@mountrouke.com
License: UNKNOWN
Platform: UNKNOWN
Requires-Python: >=3.6
